mywsgi.py
mywsgi-1.0.3.dist-info/LICENSE
mywsgi-1.0.3.dist-info/METADATA
mywsgi-1.0.3.dist-info/WHEEL
mywsgi-1.0.3.dist-info/entry_points.txt
mywsgi-1.0.3.dist-info/top_level.txt
mywsgi-1.0.3.dist-info/RECORD
