Metadata-Version: 2.1
Name: mywsgi
Version: 1.0.3
Summary: Opinionated uWSGI setup
Home-page: https://github.com/mattrobenolt/mywsgi
Author: Matt Robenolt
Author-email: matt@ydekproductions.com
License: MIT
Platform: UNKNOWN
Classifier: Development Status :: 5 - Production/Stable
Classifier: Environment :: Web Environment
Classifier: Intended Audience :: Developers
Classifier: Intended Audience :: System Administrators
Classifier: Operating System :: OS Independent
Classifier: Programming Language :: Python :: 2.7
Classifier: Programming Language :: Python :: 3
Classifier: Topic :: Software Development
